setup.py
awnb_probability/Binomialdistribution.py
awnb_probability/Gaussiandistribution.py
awnb_probability/Generaldistribution.py
awnb_probability/__init__.py
awnb_probability.egg-info/PKG-INFO
awnb_probability.egg-info/SOURCES.txt
awnb_probability.egg-info/dependency_links.txt
awnb_probability.egg-info/not-zip-safe
awnb_probability.egg-info/top_level.txt