Metadata-Version: 1.0
Name: awnb-probability
Version: 1.0
Summary: Gaussian and Binomial distributions
Home-page: UNKNOWN
Author: John Doe
Author-email: johndoe@example.com
License: UNKNOWN
Platform: UNKNOWN
